pipewire_capture/__init__.py
pipewire_capture/_native.abi3.so
pipewire_capture/py.typed
pipewire_capture-0.2.9.dist-info/METADATA
pipewire_capture-0.2.9.dist-info/WHEEL
pipewire_capture-0.2.9.dist-info/RECORD
pipewire_capture-0.2.9.dist-info/licenses/LICENSE
