Metadata-Version: 2.4
Name: pipewire-capture
Version: 0.2.9
Classifier: Development Status :: 3 - Alpha
Classifier: Intended Audience :: Developers
Classifier: License :: OSI Approved :: MIT License
Classifier: Operating System :: POSIX :: Linux
Classifier: Programming Language :: Python :: 3
Classifier: Programming Language :: Python :: 3.9
Classifier: Programming Language :: Python :: 3.10
Classifier: Programming Language :: Python :: 3.11
Classifier: Programming Language :: Python :: 3.12
Classifier: Programming Language :: Rust
Classifier: Topic :: Multimedia :: Video :: Capture
Requires-Dist: numpy>=1.20.0
License-File: LICENSE
Summary: Python library for PipeWire video capture with pre-built wheels
Keywords: pipewire,wayland,screen-capture,video,linux
Author: qube
License-Expression: MIT
Requires-Python: >=3.9
Project-URL: Homepage, https://github.com/bquenin/pipewire-capture
Project-URL: Issues, https://github.com/bquenin/pipewire-capture/issues
Project-URL: Repository, https://github.com/bquenin/pipewire-capture
